{
  "stories": {
    "world": {
      "stories": [
        {
          "headline": "Kenya transport strike over record fuel prices paralyzes major cities",
          "url": "https://x.com/BBCWorld/status/2056309864842817881",
          "handle": "BBCWorld",
          "perspectives": [
            {
              "label": "Conservative",
              "handle": "EricLDaugh",
              "url": "https://x.com/EricLDaugh/status/2055677854549971267",
              "body": "\ud83d\udea8 JUST NOW: Tommy Robinson GOES BALLISTIC to THOUSANDS of patriots on the genocide of Christians in Africa",
              "engagement": "317K views",
              "views": 317539
            },
            {
              "label": "Independent",
              "handle": "BBCWorld",
              "url": "https://x.com/BBCWorld/status/2056309864842817881",
              "body": "Strike over high fuel prices paralyses transport in Kenya",
              "engagement": "247K views",
              "views": 247846
            },
            {
              "label": "Democrat",
              "handle": "AJEnglish",
              "url": "https://x.com/AJEnglish/status/2056470417171185745",
              "body": "Several people have been killed in protest violence in Kenya where transport workers blocked roads over government fuel price hikes that took the cost of diesel to record levels.",
              "engagement": "14K views",
              "views": 14422
            }
          ]
        },
        {
          "headline": "PM Modi warns global energy crisis risks erasing decades of progress and returning massive poverty",
          "url": "https://x.com/MeghUpdates/status/2055584337236804034",
          "handle": "MeghUpdates",
          "perspectives": [
            {
              "label": "Conservative",
              "handle": "MeghUpdates",
              "url": "https://x.com/MeghUpdates/status/2055584337236804034",
              "body": "\ud83d\udea8 BIG STATEMENT\n\n\ud83c\uddee\ud83c\uddf3 PM Modi warns over the global energy crisis: \u201cThis is becoming a decade of crisis for the world.\u201d\n\n\u201cIf things don\u2019t CHANGE, the achievements of the last few decades could be ERASED and MASSIVE poverty may return.\u201d",
              "engagement": "935K views",
              "views": 935107
            },
            {
              "label": "Independent",
              "handle": "pubity",
              "url": "https://x.com/pubity/status/2055891062347256172",
              "body": "Indian Prime Minister Narendra Modi said he's worried for the future of India and the planet.\n\"First came the corona pandemic, then wars began to break out, and now there is an energy crisis. This decade is turning into a decade of disasters for the world.\"",
              "engagement": "469K views",
              "views": 469509
            },
            {
              "label": "Democrat",
              "handle": "narendramodi",
              "url": "https://x.com/narendramodi/status/2056412685848519112",
              "body": "Held fruitful talks with PM Jonas Gahr St\u00f8re in Oslo. One of the key highlights was the upgrading of our bilateral partnership to a Green Strategic Partnership, which will deepen synergy in clean energy, sustainable growth, the blue economy, green shipping and more.",
              "engagement": "257K views",
              "views": 257961
            }
          ]
        },
        {
          "headline": "WHO declares global health emergency over Ebola outbreaks in Congo and Uganda",
          "url": "https://x.com/BRICSinfo/status/2055876796919226523",
          "handle": "BRICSinfo",
          "perspectives": [
            {
              "label": "Conservative",
              "handle": "MaryBowdenMD",
              "url": "https://x.com/MaryBowdenMD/status/2056201848390918233",
              "body": "I\u2019m starting a GoFundMe to send infectious disease expert Dr Neil Stone to the Congo to flatten the curve. Thank you Neil for your courage!",
              "engagement": "42K views",
              "views": 42387
            },
            {
              "label": "Independent",
              "handle": "PopBase",
              "url": "https://x.com/PopBase/status/2055887773354094720",
              "body": "The WHO has declared the Ebola outbreak in Congo and Uganda as a public health emergency of international concern, with over 300 suspected cases and 88 deaths. They state that it does not meet the criteria of a pandemic, and that closing international borders is unnecessary.",
              "engagement": "1.4M views",
              "views": 1419344
            }
          ]
        }
      ]
    },
    "usa": {
      "stories": [
        {
          "headline": "UN top climate committee admits RCP8.5 projections were wrong after 15 years of warnings",
          "url": "https://x.com/WhiteHouse/status/2055770869847281967",
          "handle": "WhiteHouse",
          "perspectives": [
            {
              "label": "Conservative",
              "handle": "WhiteHouse",
              "url": "https://x.com/WhiteHouse/status/2055770869847281967",
              "body": "\u201cGOOD RIDDANCE! After 15 years of Dumocrats promising that \u201cClimate Change\u201d is going to destroy the Planet, the United Nations TOP Climate Committee just admitted that its own projections (RCP8.5) were WRONG! WRONG! WRONG!\u201d - President DONALD J. TRUMP \ud83c\uddfa\ud83c\uddf8",
              "engagement": "4.2M views",
              "views": 4199608
            },
            {
              "label": "Independent",
              "handle": "ABridgen",
              "url": "https://x.com/ABridgen/status/2056027101178831020",
              "body": "After decades of pushing the man-made climate change is going to destroy the planet the top UN science committee admits finally they got it wrong.",
              "engagement": "33K views",
              "views": 33606
            },
            {
              "label": "Democrat",
              "handle": "RpsAgainstTrump",
              "url": "https://x.com/RpsAgainstTrump/status/2056374809123074440",
              "body": "BREAKING: Donald Trump withdrew his $10 billion lawsuit against the IRS, allowing his lawyers and the Justice Department to settle without input from the judge overseeing the case, per NYT",
              "engagement": "49K views",
              "views": 49459
            }
          ]
        },
        {
          "headline": "Trump DOJ creates $1.776 billion fund to compensate political allies",
          "url": "https://x.com/kylegriffin1/status/2056398174894387551",
          "handle": "kylegriffin1",
          "perspectives": [
            {
              "label": "Conservative",
              "handle": "WhiteHouse",
              "url": "https://x.com/WhiteHouse/status/2056059737213411774",
              "body": "President Trump again urges the Senate to pass the SAVE America Act.",
              "engagement": "195K views",
              "views": 195628
            },
            {
              "label": "Independent",
              "handle": "nytimes",
              "url": "https://x.com/nytimes/status/2056408125704429929",
              "body": "Breaking News: The Justice Dept. announced a $1.8 billion fund to pay President Trump\u2019s allies as part of its settlement with the IRS.",
              "engagement": "680K views",
              "views": 680530
            },
            {
              "label": "Democrat",
              "handle": "kylegriffin1",
              "url": "https://x.com/kylegriffin1/status/2056398174894387551",
              "body": "BREAKING: It's official. The Trump DOJ just confirmed the creation of a $1.776 billion slush fund that can be used to pay Trump allies who claim they've been wrongfully targeted by the Biden admin's \u2018weaponization' \u2014 including, reportedly, Jan. 6 insurrectionists.",
              "engagement": "568K views",
              "views": 568306
            }
          ]
        },
        {
          "headline": "Trump urges Senate to pass SAVE America Act with voter ID provisions",
          "url": "https://x.com/america/status/2056059737213411774",
          "handle": "america",
          "perspectives": [
            {
              "label": "Conservative",
              "handle": "_Qstormrider",
              "url": "https://x.com/_Qstormrider/status/2055730723378614752",
              "body": "\ud83d\udea8 BREAKING: In a stunning blow to Democrats, 76% PERCENT of BLACK Americans want nationwide voter ID \u2014 in other words, the SAVE America Act",
              "engagement": "1.19M views",
              "views": 1198143
            },
            {
              "label": "Independent",
              "handle": "GOP_is_Gutless",
              "url": "https://x.com/GOP_is_Gutless/status/2056194459243540706",
              "body": "\ud83d\udea8 TRUMP GOES HARDBALL: President Trump is demanding Senate Republicans attach the SAVE America Act to the housing or FISA bills \u2014 both bipartisan.",
              "engagement": "16K views",
              "views": 16713
            },
            {
              "label": "Democrat",
              "handle": "america",
              "url": "https://x.com/america/status/2056059737213411774",
              "body": "President Trump again urges the Senate to pass the SAVE America Act.",
              "engagement": "195K views",
              "views": 195628
            }
          ]
        }
      ]
    },
    "business": {
      "stories": [
        {
          "handle": "burrytracker",
          "url": "https://x.com/burrytracker/status/2056348486354792785",
          "headline": "Leopold Aschenbrenner files Q1 2026 13F with big puts on tech and semis",
          "body": "Breaking: Leopold Aschenbrenner just filed his Q1 2026 13F\n\nHere's everything you need to know about his recent 13F\n\nTop 10 positions:\n\n1. VanEck Semiconductor ETF $SMH [Put] \u2014 $2.04B\n2. Nvidia $NVDA [Put] \u2014 $1.57B\n3. Oracle $ORCL [Put] \u2014 $1.07B\n4. Broadcom $AVGO [Put] \u2014 $1.01B\n5. Advanced Micro Devices $AMD [Put] \u2014 $969M\n6. Bloom Energy $BE \u2014 $879M\n7. SanDisk $SNDK \u2014 $724M\n8. Micron $MU [Put] \u2014 $584M\n9. CoreWeave $CRWV \u2014 $556M\n10. Taiwan Semiconductor $TSM [Put] \u2014 $535M\n\nNew positions:\n\n\u2022 $SMH, $NVDA, $ORCL, $AVGO, $AMD, $MU, $TSM, $ASML, $INTC, $GLW \u2014 all puts\n\u2022 $MU [Call] \u2014 $422M\n\u2022 $TSM [Call] \u2014 $355M\n\u2022 $SNDK [Call] \u2014 $389M\n\nBiggest adds:\n\n\u2022 CleanSpark $CLSK: +648% shares\n\u2022 Riot Platforms $RIOT: +87% shares\n\nBiggest trims:\n\n\u2022 CoreWeave $CRWV [Call]: -83% shares\n\u2022 Bloom Energy $BE: -36% shares\n\nFull exits:\n\n\u2022 Intel $INTC [Call] \u2014 was $747M\n\u2022 Lumentum $LITE \u2014 was $479M\n\u2022 EQT Corp $EQT \u2014 was $133M\n\u2022 Tower Semiconductor $TSEM \u2014 was $85M\n\nSummary: He kept his AI infrastructure longs and opened $8.45B in new puts against tech and semiconductor",
          "engagement": "2.1M views",
          "views": 2149631
        },
        {
          "handle": "WatcherGuru",
          "url": "https://x.com/WatcherGuru/status/2056419195076616333",
          "headline": "Kevin Warsh to be sworn in as Fed Chair on Friday replacing Powell",
          "body": "JUST IN: \ud83c\uddfa\ud83c\uddf8 Kevin Warsh to be sworn in as Fed Chair on Friday, officially replacing Jerome Powell.",
          "engagement": "127K views",
          "views": 127026
        },
        {
          "handle": "biancoresearch",
          "url": "https://x.com/biancoresearch/status/2056453629138129327",
          "headline": "Timeline of market reactions to Iran deal developments over 24 hours",
          "body": "Timeline the last 24 hours\n\nSunday night: \"Time of the Essense\" for Iranian deal ...S&P futures down\n\nTwo hours before open: Close to a deal ... S&P futures rally\n\nMorning: Not close to a deal, S&P down\n\nAftenoon: Holding off on tomorrow's attack to get a deal, S&P recovers.",
          "engagement": "43K views",
          "views": 43685
        }
      ]
    },
    "top": {
      "stories": [
        {
          "handle": "elonmusk",
          "url": "https://x.com/elonmusk/status/2056384750026178796",
          "headline": "Elon Musk promotes a book defending Western Civilization.",
          "body": "But this book for your friends for the defense of Western Civilization!",
          "engagement": "2.5M views",
          "views": 2466444
        },
        {
          "handle": "elonmusk",
          "url": "https://x.com/elonmusk/status/2056384365144183261",
          "headline": "Elon Musk replies to a post about political shifts",
          "body": "The murderous lunatic left",
          "engagement": "1.89M views",
          "views": 1890274
        },
        {
          "handle": "lotodots",
          "url": "https://x.com/lotodots/status/2056398228455624724",
          "headline": "FNAF cutscene with added sounds",
          "body": "i've gotten this cutscene about 50 timesalready so i added fnaf sounds to it",
          "engagement": "293K views",
          "views": 292967
        }
      ]
    },
    "msm": {
      "stories": [
        {
          "handle": "nytimes",
          "url": "https://x.com/nytimes/status/2056408125704429929",
          "headline": "Justice Dept. announces $1.8 billion fund for Trump allies in IRS settlement.",
          "body": "Breaking News: The Justice Dept. announced a $1.8 billion fund to pay President Trump\u2019s allies as part of its settlement with the IRS. Follow live updates. https://www.nytimes.com/live/2026/05/18/us/trump-news?smtyp=cur&smid=tw-nytimes",
          "engagement": "680K views",
          "views": 680530
        },
        {
          "handle": "nytimes",
          "url": "https://x.com/nytimes/status/2056472367690359256",
          "headline": "Security guard killed in shooting at Islamic Center of San Diego mosque.",
          "body": "Breaking News: A security guard was killed in a shooting at the Islamic Center of San Diego, the mosque\u2019s leader said. This is a developing story. https://www.nytimes.com/2026/05/18/us/san-diego-mosque-shooting.html?smtyp=cur&smid=tw-nytimes",
          "engagement": "53K views",
          "views": 52536
        },
        {
          "handle": "nytimes",
          "url": "https://x.com/nytimes/status/2056466973387555009",
          "headline": "Over 23,000 ordered to evacuate Simi Valley amid fast-moving brush fire.",
          "body": "Breaking News: More than 23,000 people were ordered to evacuate Simi Valley, California, as a fast-moving brush fire threatened homes, officials said. https://www.nytimes.com/2026/05/18/us/sandy-fire-simi-valley-california.html?smid=tw-nytimes&smtyp=cur",
          "engagement": "53K views",
          "views": 53275
        }
      ]
    },
    "sports": {
      "stories": [
        {
          "handle": "FabrizioRomano",
          "url": "https://x.com/FabrizioRomano/status/2056292538705649901",
          "headline": "Jos\u00e9 Mourinho agrees to return to Real Madrid on two-year deal",
          "body": "\ud83d\udea8 BREAKING: Jos\u00e9 Mourinho back to Real Madrid, HERE WE GO! \ud83d\udca3\ud83e\udd0d\n\nAll terms have been verbally agreed between Jos\u00e9 Mourinho and Real Madrid, waiting to sign all documents.\n\nPlan for initial two year deal, JM to travel to Madrid after Real-Bilbao game.\n\nThe Special One is back.",
          "engagement": "25.8M views",
          "views": 25762298
        },
        {
          "handle": "SkySportsPL",
          "url": "https://x.com/SkySportsPL/status/2056401854678913327",
          "headline": "PGMO admits Manchester United's goal should not have been given in Forest match",
          "body": "BREAKING: PGMO admit Manchester United's second goal during yesterday's game should not have been given. PGMO chief refereeing officer Howard Webb has talked to Forest today to acknowledge the misjudgement.",
          "engagement": "1.3M views",
          "views": 1344292
        },
        {
          "handle": "AdamSchefter",
          "url": "https://x.com/AdamSchefter/status/2056420190364037125",
          "headline": "2028 NFL Draft expected to be held in Minneapolis",
          "body": "ESPN sources: The 2028 NFL Draft is expected to be awarded to Minneapolis at this week\u2019s league meeting. The NFL\u2019s fan engagement and major events committees have been working with the city and the Vikings on plans for the 2028 Draft.",
          "engagement": "826K views",
          "views": 826010
        }
      ]
    },
    "elon": {
      "stories": [
        {
          "handle": "elonmusk",
          "url": "https://x.com/elonmusk/status/2056284797899567459",
          "headline": "Elon Musk shares a video post.",
          "body": "https://t.co/W21WWuNFVv",
          "engagement": "36.6M views",
          "views": 36590479
        },
        {
          "handle": "elonmusk",
          "url": "https://x.com/elonmusk/status/2056472426658058358",
          "headline": "Elon Musk comments on a ruling by an Oakland judge.",
          "body": "This illustrates why the ruling by the terrible activist Oakland judge, who simply used the jury as a fig leaf, creates such a terrible precedent.\n\nShe just handed out a free license to loot charities if you can keep the looting quiet for a few years!",
          "engagement": "1.7M views",
          "views": 1712523
        },
        {
          "handle": "elonmusk",
          "url": "https://x.com/elonmusk/status/2056179413901877551",
          "headline": "Elon Musk asks where AI will be in 1, 2 or 3 years.",
          "body": "Where will AI be in 1, 2 or 3 years?",
          "engagement": "33.6M views",
          "views": 33586436
        }
      ]
    },
    "pods": {
      "stories": []
    },
    "pg6": {
      "stories": [
        {
          "handle": "PopBase",
          "url": "https://x.com/PopBase/status/2056377887679271019",
          "headline": "Trisha Paytas releases K-Pop single \u2018\uc0ac\ub791\ud574 (I Love You)\u2019",
          "body": "Trisha Paytas has released a K-Pop single titled \u2018\uc0ac\ub791\ud574 (I Love You).\u2019",
          "engagement": "599K views",
          "views": 599051
        },
        {
          "handle": "PopCrave",
          "url": "https://x.com/PopCrave/status/2056136620965843172",
          "headline": "Quenlin Blackwell teases next guest on Feeding Starving Celebrities",
          "body": "Quenlin Blackwell teases the next guest on \u2018Feeding Starving Celebrities.\u2019 Who do you think it is?",
          "engagement": "1.5M views",
          "views": 1459948
        },
        {
          "handle": "allurequinn",
          "url": "https://x.com/allurequinn/status/2056139556404207698",
          "headline": "Pop culture influencer prepares to make history",
          "body": "GETTING READY                    TO MAKE HISTORY",
          "engagement": "530K views",
          "views": 530252
        }
      ]
    },
    "recipe": {
      "stories": [
        {
          "handle": "mtmtharb",
          "url": "https://x.com/mtmtharb/status/2056286814370185252",
          "headline": "Japanese pork shabu salad recipe with tomato and onion",
          "body": "\u6691\u304f\u306a\u308b\u3068\u98df\u3079\u305f\u304f\u306a\u308b1\u756a\u597d\u304d\u306a\u8c5a\u3057\u3083\u3076\u306e\u98df\u3079\u65b9\u3002\u8c5a\u8089250g\u3092\u30b5\u30c3\u3068\u8339\u3067\u3001\u30c8\u30de\u30c81\u500b\u3001\u65b0\u7389\u306d\u304e\u3001\u30aa\u30ea\u30fc\u30d6\u30aa\u30a4\u30eb\u3068\u9162\u306f\u5927\u3055\u30582\u3001\u30ec\u30e2\u30f3\u6c41\u3068\u7802\u7cd6\u306f\u5927\u3055\u30581\u3001\u5869\u5c0f\u3055\u30581/2\u3001\u30d6\u30e9\u30c3\u30af\u30da\u30c3\u30d1\u30fc\u3092\u5165\u308c\u3066\u3088\u304f\u6df7\u305c\u308b\u3002\u3042\u307e\u308a\u306b\u3082\u7f8e\u5473\u3059\u304e\u308b\u306e\u3067\u3044\u3064\u3082\u500d\u91cf\u4f5c\u3063\u3066\u3057\u307e\u3046...",
          "engagement": "491K views",
          "views": 491317
        },
        {
          "handle": "KitchenRecipes_",
          "url": "https://x.com/KitchenRecipes_/status/2056426868954353777",
          "headline": "Quick cake recipe made in a toast machine",
          "body": "Cake in the toast machine",
          "engagement": "94K views",
          "views": 94092
        },
        {
          "handle": "MorinagaIce",
          "url": "https://x.com/MorinagaIce/status/2056283648182366569",
          "headline": "Promotion for new caramel pudding ice cream with giveaway.",
          "body": "\ud83c\udf6e\u4f53\u9a13\u578b\u30a2\u30a4\u30b9\ud83c\udf6e\n\u30de\u30df\u30fc\u30ec\uff1c\u30ad\u30e3\u30e9\u30e1\u30ea\u30c3\u30af\u30d7\u30c7\u30a3\u30f3\u30b0\uff1e\u767a\u58f2\u8a18\u5ff5\nAmazon\u30ae\u30d5\u30c8\u30ab\u30fc\u30c91,000\u5186\u5206\u309210\u540d\u306b\ud83c\udf81\n\n\u2460@MorinagaIce \u3092\u30d5\u30a9\u30ed\u30fc\n\u2461\u672c\u6295\u7a3f\u3092\u672c\u65e524\u6642\u307e\u3067\u306b\u30ea\u30dd\u30b9\u30c8\n\u2462\uff03\u3053\u306e\u3068\u3045\u308b\u308d\u308d\u304a\u3049\u3049\u304a\u611f\u3092\u6c42\u3081\u30661500\u65e5 \u3092\u30ea\u30d7\u30e9\u30a4\u3067\u78ba\u7387UP\n\nCV:\uff03\u5ca1\u672c\u4fe1\u5f66",
          "engagement": "265K views",
          "views": 264861
        }
      ]
    },
    "science": {
      "stories": [
        {
          "handle": "elonmusk",
          "url": "https://x.com/elonmusk/status/2056288621980708908",
          "headline": "Elon Musk shares update on advanced tech development",
          "body": "https://t.co/52kpZrjXWA",
          "engagement": "44.9M views",
          "views": 44893178
        },
        {
          "handle": "elonmusk",
          "url": "https://x.com/elonmusk/status/2056179413901877551",
          "headline": "Elon Musk questions future of AI over next 1-3 years",
          "body": "Where will AI be in 1, 2 or 3 years?",
          "engagement": "16.3M views",
          "views": 16350092
        },
        {
          "handle": "elonmusk",
          "url": "https://x.com/elonmusk/status/2056280661850259922",
          "headline": "Elon Musk reacts to AI compared to Industrial Revolution steam engine breakthrough",
          "body": "\ud83d\udd25\ud83d\udd25",
          "engagement": "10.3M views",
          "views": 10260394
        }
      ]
    },
    "local": {
      "stories": [
        {
          "handle": "KTLA",
          "url": "https://x.com/KTLA/status/2056174452031754479",
          "headline": "SoCal woman seriously injured in fall while vacationing in Mexico",
          "body": "The woman is still hospitalized in Mexico with a broken back.\nRead more: https://ktla.com/news/local-news/socal-woman-seriously-injured-in-fall-while-vacationing-in-mexico/",
          "engagement": "8.7K views",
          "views": 8714
        },
        {
          "handle": "ABC7",
          "url": "https://x.com/ABC7/status/2056358647383339400",
          "headline": "Windy Monday with light Santa Ana winds expected across SoCal",
          "body": "Windy Monday: Light Santa Ana winds expected across SoCal before warmer temps move in this week. Your forecast now on ABC7 https://abc7.com/post/los-angeles-weather-temperatures-southern-california/58983/",
          "engagement": "2K views",
          "views": 2123
        }
      ]
    },
    "conspiracy": {
      "stories": [
        {
          "handle": "Patrickwebb",
          "url": "https://x.com/Patrickwebb/status/2056180842532397163",
          "headline": "CIA whistleblower claims cover-up of directed energy attacks causing Havana Syndrome",
          "body": "BREAKING: CIA whistleblower alleges the agency is covering up evidence that Havana Syndrome and Anomalous Health Incidents (AHIs) are caused by directed energy attacks resulting in debilitating neurological symptoms and injuries, per Catherine Herridge.",
          "engagement": "102K views",
          "views": 102487
        },
        {
          "handle": "5149jamesli",
          "url": "https://x.com/5149jamesli/status/2056181542909890623",
          "headline": "Deep state alleged to have attempted honeypot on Rep. Thomas Massie",
          "body": "So the deep state attempted a failed honeypot operation on Thomas Massie?! \ud83e\uddd0\ud83d\ude2d",
          "engagement": "52.9K views",
          "views": 52914
        },
        {
          "handle": "PainterGroyper",
          "url": "https://x.com/PainterGroyper/status/2056266234497470774",
          "headline": "Government conspiracy involving extraterrestrial conditioning",
          "body": "Government conspiracy to condition us to extra veiny extraterrestrial purple cock",
          "engagement": "33145 views",
          "views": 33145
        }
      ]
    },
    "comedy": {
      "stories": [
        {
          "handle": "found_it_funny",
          "url": "https://x.com/found_it_funny/status/2056366778490450317",
          "headline": "Humorous image or meme shared by funny account",
          "body": "https://t.co/lPIuxst5Bq",
          "engagement": "398K views",
          "views": 398860
        },
        {
          "handle": "found_it_funny",
          "url": "https://x.com/found_it_funny/status/2056404564526436590",
          "headline": "Humorous image or meme shared by funny account",
          "body": "https://t.co/LKnzbw4KNL",
          "engagement": "115K views",
          "views": 115787
        },
        {
          "handle": "ClownWorld",
          "url": "https://x.com/ClownWorld/status/2056292011120972027",
          "headline": "Viral video captioned 'Not funny at all' sparks laughs",
          "body": "Not funny at all",
          "engagement": "244K views",
          "views": 244017
        }
      ]
    }
  },
  "last_updated": "2026-05-18T21:13:33.681592"
}